ovos_tts_plugin_marytts/__init__.py
ovos_tts_plugin_marytts/version.py
ovos_tts_plugin_marytts-0.1.0.dist-info/licenses/LICENSE
ovos_tts_plugin_marytts-0.1.0.dist-info/METADATA
ovos_tts_plugin_marytts-0.1.0.dist-info/WHEEL
ovos_tts_plugin_marytts-0.1.0.dist-info/entry_points.txt
ovos_tts_plugin_marytts-0.1.0.dist-info/top_level.txt
ovos_tts_plugin_marytts-0.1.0.dist-info/zip-safe
ovos_tts_plugin_marytts-0.1.0.dist-info/RECORD
