Metadata-Version: 2.4
Name: ovos_tts_plugin_marytts
Version: 0.1.0
Summary: A marytts plugin for OpenVoiceOS
Home-page: https://github.com/OpenVoiceOS/ovos-tts-plugin-marytts
Author: jarbasAi
Author-email: jarbasai@mailfence.com
License: Apache2
Keywords: mycroft plugin tts
Classifier: Intended Audience :: Developers
Classifier: Topic :: Text Processing :: Linguistic
Classifier: Programming Language :: Python :: 3.6
License-File: LICENSE
Requires-Dist: ovos-plugin-manager<=3.0.0,>=1.0.0
Dynamic: author
Dynamic: author-email
Dynamic: classifier
Dynamic: home-page
Dynamic: keywords
Dynamic: license
Dynamic: license-file
Dynamic: requires-dist
Dynamic: summary
